sgg/__init__.py
sgg/__main__.py
sgg/ext.py
sgg-0.0.5.dist-info/LICENSE
sgg-0.0.5.dist-info/METADATA
sgg-0.0.5.dist-info/WHEEL
sgg-0.0.5.dist-info/entry_points.txt
sgg-0.0.5.dist-info/top_level.txt
sgg-0.0.5.dist-info/RECORD
