Metadata-Version: 2.1
Name: sgg
Version: 0.0.5
Summary: Simple Graph Generator
Home-page: https://github.com/thiagotps/sgg
Author: Thiago T. P. Silva
Author-email: thiagoteodoro501@gmail.com
License: UNKNOWN
Keywords: matplotlib graph
Platform: UNKNOWN
Classifier: Programming Language :: Python :: 3
Classifier: License :: OSI Approved :: MIT License
Classifier: Operating System :: OS Independent
Requires-Python: >=3.5.2
License-File: LICENSE
Requires-Dist: matplotlib
